Metadata-Version: 2.1
Name: cows
Version: 1.0.1
Summary: Simple, efficient collections for strings with
Home-page: https://github.com/arosenfeld/cows
Author: Aaron M. Rosenfeld
Author-email: aaron@rosenfeld.io
License: UNKNOWN
Platform: UNKNOWN
